pytest_parametrize/__init__.py
pytest_parametrize/parametrize.py
pytest_parametrize/py.typed
pytest_parametrize-1.5.0.dist-info/METADATA
pytest_parametrize-1.5.0.dist-info/WHEEL
pytest_parametrize-1.5.0.dist-info/licenses/LICENSE
pytest_parametrize-1.5.0.dist-info/RECORD
