Metadata-Version: 2.4
Name: pytest-parametrize
Version: 1.5.0
Summary: pytest decorator for parametrizing test cases in a dict-way
License: MIT
License-File: LICENSE
Keywords: pytest,parametrize,testing
Author: Marcin Skrobczyński
Author-email: marcin@skrobczynski.pl
Requires-Python: >=3.9,<4.0
Classifier: Development Status :: 5 - Production/Stable
Classifier: Environment :: Console
Classifier: Framework :: Pytest
Classifier: Intended Audience :: Developers
Classifier: License :: OSI Approved :: MIT License
Classifier: Operating System :: OS Independent
Classifier: Programming Language :: Python :: 3
Classifier: Programming Language :: Python :: 3.9
Classifier: Programming Language :: Python :: 3.10
Classifier: Programming Language :: Python :: 3.11
Classifier: Programming Language :: Python :: 3.12
Classifier: Programming Language :: Python :: 3.13
Classifier: Programming Language :: Python :: 3.14
Classifier: Programming Language :: Python :: Implementation :: CPython
Classifier: Topic :: Software Development :: Libraries :: Python Modules
Classifier: Topic :: Software Development :: Testing
Requires-Dist: pytest (>=8.3.0,<9.0.0)
Project-URL: Homepage, https://github.com/MarcinSkrobczynski/pytest-parametrize
